gpt_toolbox.py
gpt_toolbox-0.1.3.dist-info/METADATA
gpt_toolbox-0.1.3.dist-info/WHEEL
gpt_toolbox-0.1.3.dist-info/top_level.txt
gpt_toolbox-0.1.3.dist-info/RECORD
