Metadata-Version: 2.1
Name: gpt-toolbox
Version: 0.1.3
Requires-Dist: openai
Requires-Dist: weaviate-client
Requires-Dist: tiktoken
Requires-Dist: langchain
